openbuffet_logger/__init__.py
openbuffet_logger/logger_manager.py
openbuffet_logger/interfaces/__init__.py
openbuffet_logger/interfaces/ilogger_service.py
openbuffet_logger/services/__init__.py
openbuffet_logger/services/logging_logger_service.py
openbuffet_logger-0.1.0.dist-info/licenses/LICENSE
openbuffet_logger-0.1.0.dist-info/METADATA
openbuffet_logger-0.1.0.dist-info/WHEEL
openbuffet_logger-0.1.0.dist-info/top_level.txt
openbuffet_logger-0.1.0.dist-info/RECORD
